icerok_server/__init__.py
icerok_server/main.py
icerok_server/version.py
icerok_server-0.1.13.dist-info/entry_points.txt
icerok_server-0.1.13.dist-info/LICENSE
icerok_server-0.1.13.dist-info/WHEEL
icerok_server-0.1.13.dist-info/METADATA
icerok_server-0.1.13.dist-info/RECORD
